calysto_scheme/__init__.py
calysto_scheme/__main__.py
calysto_scheme/kernel.py
calysto_scheme/scheme.py
calysto_scheme/images/logo-32x32.png
calysto_scheme/images/logo-512x512.png
calysto_scheme/images/logo-64x64.png
calysto_scheme/modules/equality_predicates.ss
calysto_scheme/modules/sllgen.ss
calysto_scheme/modules/test_all.ss
calysto_scheme-1.4.8.data/data/share/jupyter/kernels/calysto_scheme/kernel.json
calysto_scheme-1.4.8.data/data/share/jupyter/kernels/calysto_scheme/logo-32x32.png
calysto_scheme-1.4.8.data/data/share/jupyter/kernels/calysto_scheme/logo-512x512.png
calysto_scheme-1.4.8.data/data/share/jupyter/kernels/calysto_scheme/logo-64x64.png
calysto_scheme-1.4.8.data/scripts/calysto-scheme
calysto_scheme-1.4.8.data/scripts/calysto-scheme-debug
calysto_scheme-1.4.8.dist-info/LICENSE.txt
calysto_scheme-1.4.8.dist-info/METADATA
calysto_scheme-1.4.8.dist-info/WHEEL
calysto_scheme-1.4.8.dist-info/top_level.txt
calysto_scheme-1.4.8.dist-info/RECORD
