Metadata-Version: 2.1
Name: calysto-scheme
Version: 1.4.8
Summary: A Scheme kernel for Jupyter that can use Python libraries
Home-page: https://github.com/Calysto/calysto_scheme
Author: Douglas Blank
Author-email: doug.blank@gmail.com
Platform: Any
Classifier: Framework :: IPython
Classifier: License :: OSI Approved :: BSD License
Classifier: Programming Language :: Python :: 3
Classifier: Programming Language :: Python :: 2
Classifier: Programming Language :: Scheme
Classifier: Topic :: System :: Shells
License-File: LICENSE.txt
Requires-Dist: metakernel
Requires-Dist: yasi
